README.md
setup.py
hrmtools/__init__.py
hrmtools/config.py
hrmtools.egg-info/PKG-INFO
hrmtools.egg-info/SOURCES.txt
hrmtools.egg-info/dependency_links.txt
hrmtools.egg-info/requires.txt
hrmtools.egg-info/top_level.txt
hrmtools/config/devices.yaml
hrmtools/db/__init__.py
hrmtools/db/filters.py
hrmtools/devices/__init__.py
hrmtools/devices/api.py
hrmtools/devices/cls.py
hrmtools/devices/io.py
hrmtools/devices/ioxls.py
hrmtools/devices/keys.py
hrmtools/io/__init__.py
hrmtools/io/ioconfig.py
hrmtools/servers/__init__.py
hrmtools/servers/device_list.py