Metadata-Version: 2.1
Name: hrmtools
Version: 0.1.dev4
Summary: UNKNOWN
Home-page: UNKNOWN
Author: Sylvain Guieu
Author-email: sylvain.guieu@univ-grenoble-alpes.fr
License: Creative Commons Attribution-Noncommercial-Share Alike license
Platform: UNKNOWN
